worker/VERSION
worker/__init__.py
worker/__main__.py
worker/action.py
worker/action_task.py
worker/api_client.py
worker/celery_utils.py
worker/config.py
worker/njinnworker.py
worker/packinstall.py
worker/postprocess.py
worker/shared_logging.py
worker/tasks.py
worker/utils.py
worker/version_utils.py
njinn_worker-0.12.9.dist-info/METADATA
njinn_worker-0.12.9.dist-info/WHEEL
njinn_worker-0.12.9.dist-info/entry_points.txt
njinn_worker-0.12.9.dist-info/top_level.txt
njinn_worker-0.12.9.dist-info/RECORD
