Metadata-Version: 2.1
Name: njinn-worker
Version: 0.12.9
Summary: Njinn Worker
Home-page: UNKNOWN
Author: Njinn Technologies GmbH
Author-email: contact@njinn.io
License: Other/Proprietary License
Platform: UNKNOWN
Classifier: License :: Other/Proprietary License
Classifier: Programming Language :: Python :: 3
Classifier: Programming Language :: Python :: 3.7
Classifier: Programming Language :: Python :: 3.8
Classifier: Programming Language :: Python :: 3.9
Classifier: Programming Language :: Python :: Implementation :: CPython
Classifier: Operating System :: OS Independent
Requires-Python: >=3.7, <3.10
Requires-Dist: requests (<2.26,>=2.25)
Requires-Dist: PyJWT (==1.7.1)
Requires-Dist: requests-jwt (==0.5.3)
Requires-Dist: backoff (==1.10.0)
Requires-Dist: cryptography (==3.4.7)
Requires-Dist: celery (<4.5,>=4.4)
Requires-Dist: gitpython (<2.2,>=2.1)
Requires-Dist: virtualenv (~=16.7.9)
Requires-Dist: filelock (<3.1,>=3.0)
Requires-Dist: click (<7.2,>=7.1)
